resnet/__init__.py
load_resnet-0.0.1.dist-info/LICENSE
load_resnet-0.0.1.dist-info/METADATA
load_resnet-0.0.1.dist-info/WHEEL
load_resnet-0.0.1.dist-info/top_level.txt
load_resnet-0.0.1.dist-info/RECORD
