Metadata-Version: 2.1
Name: load-resnet
Version: 0.0.1
Summary: A package to load resnet, made using PyTorch
Home-page: https://github.com/33-Papers/Deep-Residual-Learning-for-Image-Recognition
Author: Mridul Sharma
Author-email: mridulsharma3301@gmail.com
License: MIT
Classifier: License :: OSI Approved :: MIT License
Classifier: Programming Language :: Python :: 3.10
Classifier: Operating System :: OS Independent
Requires-Python: >=3.10
License-File: LICENSE
Requires-Dist: bson (>=0.5.10)
Requires-Dist: torch (==2.0.1)
Requires-Dist: torchinfo (==1.8.0)
Requires-Dist: torchvision (==0.15.2)
Provides-Extra: dev
Requires-Dist: pytest (>=7.0) ; extra == 'dev'
Requires-Dist: twine (>=4.0.2) ; extra == 'dev'
